fastapi_filter_sort/__init__.py
fastapi_filter_sort/builder.py
fastapi_filter_sort/core.py
fastapi_filter_sort/dependencies.py
fastapi_filter_sort/operators.py
fastapi_filter_sort/params.py
fastapi_filter_sort/utils.py
fastapi_filter_sort-0.1.5.dist-info/LICENSE
fastapi_filter_sort-0.1.5.dist-info/METADATA
fastapi_filter_sort-0.1.5.dist-info/WHEEL
fastapi_filter_sort-0.1.5.dist-info/RECORD
